README.md
setup.py
requests_qwd/__init__.py
requests_qwd/__version__.py
requests_qwd/_internal_utils.py
requests_qwd/adapters.py
requests_qwd/api.py
requests_qwd/auth.py
requests_qwd/certs.py
requests_qwd/compat.py
requests_qwd/cookies.py
requests_qwd/exceptions.py
requests_qwd/help.py
requests_qwd/hooks.py
requests_qwd/models.py
requests_qwd/packages.py
requests_qwd/sessions.py
requests_qwd/status_codes.py
requests_qwd/structures.py
requests_qwd/utils.py
requests_qwd.egg-info/PKG-INFO
requests_qwd.egg-info/SOURCES.txt
requests_qwd.egg-info/dependency_links.txt
requests_qwd.egg-info/top_level.txt