Metadata-Version: 2.1
Name: requests-qwd
Version: 0.1.3
Summary: A small package
Home-page: https://github.com/pypa/sampleproject
Author: zyb
Author-email: 1052350468@qq.com
License: MIT
Platform: UNKNOWN
Classifier: Programming Language :: Python :: 3
Classifier: License :: OSI Approved :: MIT License
Classifier: Operating System :: OS Independent
Requires-Python: >=3.6
